kelvin/logs.py
kelvin/py.typed
kelvin/application/__init__.py
kelvin/application/api_client.py
kelvin/application/client.py
kelvin/application/config.py
kelvin/application/filters.py
kelvin/application/stream.py
kelvin/application/timer.py
kelvin/application/version.py
kelvin/application/window.py
kelvin/config/__init__.py
kelvin/config/appyaml.py
kelvin/config/common.py
kelvin/config/exporter.py
kelvin/config/external.py
kelvin/config/importer.py
kelvin/config/manifest.py
kelvin/config/parser.py
kelvin/config/smart_app.py
kelvin/message/__init__.py
kelvin/message/base_messages.py
kelvin/message/evidences.py
kelvin/message/krn.py
kelvin/message/message.py
kelvin/message/msg_builders.py
kelvin/message/msg_type.py
kelvin/message/primitives.py
kelvin/message/runtime_manifest.py
kelvin/message/typing.py
kelvin/message/utils.py
kelvin/publisher/__init__.py
kelvin/publisher/csv_publisher.py
kelvin/publisher/main.py
kelvin/publisher/server.py
kelvin/publisher/simulator.py
kelvin_python_sdk-0.3.1.dist-info/METADATA
kelvin_python_sdk-0.3.1.dist-info/WHEEL
kelvin_python_sdk-0.3.1.dist-info/entry_points.txt
kelvin_python_sdk-0.3.1.dist-info/top_level.txt
kelvin_python_sdk-0.3.1.dist-info/RECORD
