Metadata-Version: 2.4
Name: kelvin-python-sdk
Version: 0.3.1
Summary: Framework for Kelvin application development
Author-email: Kelvin Inc <engineering@kelvininc.com>
Classifier: Operating System :: OS Independent
Classifier: Programming Language :: Python :: 3
Requires-Python: <3.14,>=3.9
Requires-Dist: pydantic==2.11.*
Requires-Dist: pydantic-settings==2.*
Requires-Dist: structlog==23.*
Requires-Dist: PyYAML==6.*
Requires-Dist: kelvin-krn<0.2,>=0.1.1
Requires-Dist: kelvin-python-api-client<2.0,>=1.0.1
Provides-Extra: publisher
Requires-Dist: click==8.*; extra == "publisher"
Requires-Dist: arrow==1.*; extra == "publisher"
Provides-Extra: ai
Requires-Dist: pandas==2.*; extra == "ai"
